casting_expert/__init__.py
casting_expert/cli.py
casting_expert/core.py
casting_expert/validators.py
casting_expert/casters/__init__.py
casting_expert/casters/parsers.py
casting_expert/casters/serializers.py
casting_expert/casters/type_inference.py
casting_expert/casters/validators.py
casting_expert-0.1.7.dist-info/METADATA
casting_expert-0.1.7.dist-info/WHEEL
casting_expert-0.1.7.dist-info/entry_points.txt
casting_expert-0.1.7.dist-info/licenses/LICENSE
casting_expert-0.1.7.dist-info/RECORD
