Metadata-Version: 2.3
Name: casting-expert
Version: 0.1.7
Summary: A comprehensive Python package for type casting, conversion, and validation with advanced features
Project-URL: Homepage, https://github.com/ahmednizami/casting-expert
Project-URL: Documentation, https://github.com/ahmednizami/casting-expert
Project-URL: Bug Tracker, https://github.com/ahmednizami/casting-expert/issues
Project-URL: Changelog, https://github.com/ahmednizami/casting-expert/blob/main/CHANGELOG.md
Author-email: Muhammad Ahmed Saeed <ahmednizami2021@gmail.com>
Keywords: cli,data conversion,data processing,data transformation,dictionary conversion,json,schema validation,string parsing,type casting,type inference,validation,yaml
Classifier: Development Status :: 4 - Beta
Classifier: Environment :: Console
Classifier: Environment :: Web Environment
Classifier: Intended Audience :: Developers
Classifier: Intended Audience :: Education
Classifier: Intended Audience :: End Users/Desktop
Classifier: Intended Audience :: Financial and Insurance Industry
Classifier: Intended Audience :: Healthcare Industry
Classifier: Intended Audience :: Information Technology
Classifier: Intended Audience :: Science/Research
Classifier: Intended Audience :: System Administrators
Classifier: License :: OSI Approved :: MIT License
Classifier: Operating System :: OS Independent
Classifier: Programming Language :: Python :: 3
Classifier: Programming Language :: Python :: 3.7
Classifier: Programming Language :: Python :: 3.8
Classifier: Programming Language :: Python :: 3.9
Classifier: Programming Language :: Python :: 3.10
Classifier: Programming Language :: Python :: 3.11
Classifier: Programming Language :: Python :: 3.12
Classifier: Topic :: Software Development :: Build Tools
Classifier: Topic :: Software Development :: Libraries
Classifier: Topic :: Software Development :: Libraries :: Python Modules
Classifier: Topic :: Text Processing
Classifier: Topic :: Utilities
Classifier: Typing :: Typed
Requires-Python: >=3.7
Requires-Dist: python-dateutil>=2.7.0
Requires-Dist: typing-extensions>=3.7.4
Provides-Extra: dev
Requires-Dist: black>=21.0.0; extra == 'dev'
Requires-Dist: flake8>=3.9.0; extra == 'dev'
Requires-Dist: isort>=5.0.0; extra == 'dev'
Requires-Dist: mypy>=0.900; extra == 'dev'
Requires-Dist: pytest-cov>=2.10.0; extra == 'dev'
Requires-Dist: pytest>=6.0.0; extra == 'dev'
Provides-Extra: yaml
Requires-Dist: pyyaml>=5.1; extra == 'yaml'
